{
    "bot_public": true,
    "bot_require_code_grant": false,
    "description": "",
    "executables": [
        {
            "is_launcher": false,
            "name": "street fighter 30th anniversary collection/sf30thanniversarycollection.exe",
            "os": "win32"
        }
    ],
    "flags": 0,
    "hook": true,
    "icon": "e8d42836fc7499f0e8dd2137c96e8fab",
    "id": "1124353826565140561",
    "name": "Street Fighter 30th Anniversary Collection",
    "publishers": [
        {
            "id": "1124353827076853831",
            "name": "Digital Eclipse"
        }
    ],
    "summary": "",
    "third_party_skus": [
        {
            "distributor": "steam",
            "id": "586200",
            "sku": "586200"
        }
    ],
    "type": 1,
    "verify_key": "46dd873e01efa61d159957246231f5e76b065caf93e8a06eea3747afad37aa38"
}