{
    "bot_public": true,
    "bot_require_code_grant": false,
    "description": "",
    "executables": [
        {
            "is_launcher": false,
            "name": "dead effect 2/deadeffect2.exe",
            "os": "win32"
        }
    ],
    "flags": 0,
    "hook": true,
    "icon": "d7b85a7795119e7af3a8ac15b3e69164",
    "id": "1124357011858014321",
    "name": "Dead Effect 2",
    "publishers": [
        {
            "id": "1124357012340355092",
            "name": "BadFly Interactive, a.s."
        }
    ],
    "summary": "",
    "third_party_skus": [
        {
            "distributor": "steam",
            "id": "394760",
            "sku": "394760"
        }
    ],
    "type": 1,
    "verify_key": "a2e6a199bb73b57dc143e143d58918a807552e1c96388aaf7bd1017ec4146b2e"
}