{
    "aliases": [
        "Mafia - Definitve Edition",
        "Mafia: Definitive Edition"
    ],
    "executables": [
        {
            "is_launcher": false,
            "name": "mafia - definitive edition/mafiadefinitiveedition.exe",
            "os": "win32"
        },
        {
            "is_launcher": false,
            "name": "mafia definitive edition/mafiadefinitiveedition.exe",
            "os": "win32"
        }
    ],
    "hook": true,
    "id": "1174042614765457508",
    "name": "Mafia: Definitive Edition"
}