{
    "aliases": [
        "Digimon Masters Online"
    ],
    "executables": [
        {
            "is_launcher": false,
            "name": "digimon masters online - steam/gdmo.exe",
            "os": "win32"
        },
        {
            "is_launcher": false,
            "name": "dmlauncher.exe",
            "os": "win32"
        },
        {
            "is_launcher": false,
            "name": "digimon masters online - steam/updatemanager.exe",
            "os": "win32"
        }
    ],
    "hook": true,
    "id": "451544305509859328",
    "name": "Digimon Masters Online"
}