{
    "description": "",
    "executables": [
        {
            "is_launcher": false,
            "name": "system/witcher.exe",
            "os": "win32"
        }
    ],
    "flags": 0,
    "hook": true,
    "icon": "41584f116adbd6dd064129615a483575",
    "id": "484451241825533962",
    "name": "The Witcher Enhanced Edition Director's Cut",
    "summary": "",
    "third_party_skus": [
        {
            "distributor": "gog",
            "id": "",
            "sku": ""
        }
    ],
    "type": 1,
    "verify_key": "92a49efc9df32c8dc0e5b5e9001b19c5516c159f8e2f0f90c06302f9828cfe00"
}